test1277/__init__.py
test1277/live-scraping-firebase-adminsdk-gck9g-011e4f00e1.json
test1277/script_tracker.py
test1277-0.1.dist-info/METADATA
test1277-0.1.dist-info/WHEEL
test1277-0.1.dist-info/top_level.txt
test1277-0.1.dist-info/RECORD
